neon_api_proxy/__init__.py
neon_api_proxy/__main__.py
neon_api_proxy/alpha_vantage_api.py
neon_api_proxy/api_connector.py
neon_api_proxy/cached_api.py
neon_api_proxy/config.py
neon_api_proxy/controller.py
neon_api_proxy/owm_api.py
neon_api_proxy/socket_handler.py
neon_api_proxy/test_api.py
neon_api_proxy/wolfram_api.py
neon_api_proxy/client/__init__.py
neon_api_proxy/client/alpha_vantage.py
neon_api_proxy/client/financial_modeling_prep.py
neon_api_proxy/client/map_maker.py
neon_api_proxy/client/open_weather_map.py
neon_api_proxy/client/wolfram_alpha.py
neon_api_proxy/services/__init__.py
neon_api_proxy/services/alpha_vantage_api.py
neon_api_proxy/services/map_maker_api.py
neon_api_proxy/services/owm_api.py
neon_api_proxy/services/test_api.py
neon_api_proxy/services/wolfram_api.py
neon_api_proxy-0.7.0.dist-info/LICENSE.md
neon_api_proxy-0.7.0.dist-info/METADATA
neon_api_proxy-0.7.0.dist-info/WHEEL
neon_api_proxy-0.7.0.dist-info/entry_points.txt
neon_api_proxy-0.7.0.dist-info/top_level.txt
neon_api_proxy-0.7.0.dist-info/zip-safe
neon_api_proxy-0.7.0.dist-info/RECORD
