Metadata-Version: 2.1
Name: neon-api-proxy
Version: 0.7.0
Summary: Neon Proxy for external API Calls
Home-page: https://github.com/NeonGeckoCom/neon_api_proxy
Author: Neongecko
Author-email: developers@neon.ai
License: NeonAI License v1.0
Classifier: Intended Audience :: Developers
Classifier: Programming Language :: Python :: 3.6
License-File: LICENSE.md
Requires-Dist: requests-cache>=0.6.4,~=0.6
Requires-Dist: requests~=2.20
Requires-Dist: neon-utils[network]~=1.0
Requires-Dist: ovos-utils<0.2.0,>=0.0.31
Requires-Dist: ovos-config~=0.0.10
Requires-Dist: neon-mq-connector~=0.7
